{
  "game_title": "对齐·颗粒度·吃瓜循环 · 健身限定版",
  "subtitle": "为团建包间定制 · 5 人快节奏局",
  "premise": "每人抽一张密语卡，上面写着一个开会黑话(对齐/颗粒度/闭环/抓手/落地)。你需要在每轮偷偷让别人说出你的词——但别被发现。同时，健身狂魔在暗中埋下一个体能炸弹。节奏快，混乱高，5 人局。",
  "players": ["阿凯", "琳琳", "老周", "小雨", "Tony"],
  "props_dealt": [
    { "prop": "密语卡", "to": "全体", "visibility": "自己看", "note": "每人一张，写着你专属的「开会黑话」词(对齐/颗粒度/闭环/抓手/落地)，不能让任何人看到。" },
    { "prop": "匿名投票器", "to": "全体", "visibility": "自己看", "note": "每轮用做「是谁在钓鱼」的投票，亮票时自动转全场公开。" },
    { "prop": "定时炸弹", "to": "Tony(首持)", "visibility": "全场公开", "note": "道具内置随机倒计时，Tony 拿到后需要想办法传给下家。" },
    { "prop": "记分板", "to": "公共区", "visibility": "全场公开", "note": "记录每轮积分。" }
  ],
  "flow": [
    "开局: 每人抽密语卡，读自己的黑话词，记住它，绝不能暴露。",
    "每轮: 主持人提一个「吃瓜话题」(如：谁最内卷？谁最爱摸鱼？)，每人必须围绕话题说一句话，并**自然**带出自己的黑话词，不准重复上一轮用过的句子结构。",
    "说完后，所有人匿名投票：「谁刚才在故意带词？」。被最多票者接受下一步。",
    "若被指者确实带了词(且不是被冤枉) → 他成功把词安插进对话，获得 +1 分，并触发「健身炸弹」——从 Tony 开始传递定时炸弹，传一圈后炸到的人做 10 秒波比跳(惩罚轻)。",
    "若被指者是被冤枉(并没带词) → 投票的发起人/指向者中随机选一人接受惩罚(轻)：做 10 秒平板支撑。",
    "若有人**故意在对话中说别人的词**(即非自己密语卡上的词) → 被指并确认后，**惩罚(中)**：该人做 20 秒开合跳，且当前轮不计分。",
    "游戏持续 6 轮，或有人累积 3 分即获胜。",
    "平局/并列默认由系统随机裁决(如转盘掷骰)。"
  ],
  "rules": [
    {
      "flavor_name": "开会黑话·密令",
      "mechanic": "判定",
      "plain_rule": "每轮发言中，你必须自然说出自己密语卡上的词(对齐/颗粒度/闭环/抓手/落地)。系统只判定你是否用了那个词——别人听不听得懂无所谓。说漏了 = 本轮不得分。故意说别人的词 = 被指后罚中。",
      "visibility": "自己看"
    },
    {
      "flavor_name": "吃瓜雷达",
      "mechanic": "同时提交",
      "plain_rule": "每轮发言结束后，所有人匿名投票「谁在故意带词」。可以投自己，可以弃票。结算规则：得票最多者进入验证环节；若平票，全场一起用匿名投票器再投一轮，再平则系统随机选。",
      "visibility": "自己看"
    },
    {
      "flavor_name": "健身炸弹",
      "mechanic": "转移",
      "plain_rule": "当有人成功带词并被指中(即他被指且他确实带了词)，他从 Tony(首持者)那里接过定时炸弹，必须传给下一个人(顺时针)。传完一轮后若炸弹还在某个人手里，到点炸——他做 10 秒波比跳(惩罚轻)。若炸弹未传完一轮就炸，则当前持有者做惩罚(轻)。",
      "visibility": "全场公开"
    },
    {
      "flavor_name": "冤枉了",
      "mechanic": "惩罚(轻)",
      "plain_rule": "若被投票指中的人其实没带词(冤枉)，则从投票给他的人中随机选一人做 10 秒平板支撑。若被指者弃票则跳过。",
      "visibility": "全场公开"
    },
    {
      "flavor_name": "偷词者",
      "mechanic": "惩罚(中)",
      "plain_rule": "若有人在对话中故意说出别人的密语词(非自己的词)，且被当场质疑并投票确认，此人做 20 秒开合跳，且本轮不得分。质疑方式：发言结束后，任何人在投票前可大声喊「偷词！」并指名道姓，大家立即用匿名投票器确认是否偷词。若投票确认(过半) → 惩罚(中)；若未确认 → 喊话者自己接受惩罚(轻)。",
      "visibility": "全场公开"
    },
    {
      "flavor_name": "颗粒度不够",
      "mechanic": "惩罚(重)",
      "plain_rule": "累计被冤枉 2 次的人，接受一次「终极对齐」：做 30 秒高抬腿，并全场喊一遍他的黑话词。之后清零冤枉计数。",
      "visibility": "全场公开"
    }
  ],
  "reveal_text": "对齐了颗粒度，闭环了吃瓜——最后发现，最会带节奏的，是那个总喊着要落地的人。",
  "reveal_signature": "融合自 老周 的「开会黑话」 × 小雨 的「爱吃瓜」 × Tony 的「健身狂魔」",
  "flavor_glossary": [
    { "term": "对齐", "means": "开会黑话，指达成共识/同步信息。这里作为一个密语词。" },
    { "term": "颗粒度", "means": "开会黑话，指细化程度/细节。这里作为一个密语词。" },
    { "term": "闭环", "means": "开会黑话，指形成一个完整的流程循环。这里作为一个密语词。" },
    { "term": "抓手", "means": "开会黑话，指切入点/着力点。这里作为一个密语词。" },
    { "term": "落地", "means": "开会黑话，指计划被真正实施。这里作为一个密语词。" },
    { "term": "波比跳", "means": "健身动作：站立→深蹲→俯卧撑→跳跃，连续做 10 秒。" },
    { "term": "平板支撑", "means": "健身动作：俯卧、用前臂和脚尖支撑身体，保持 10 秒。" },
    { "term": "开合跳", "means": "健身动作：站立→跳起双脚分开、双手过头→跳回并拢。20 秒。" },
    { "term": "高抬腿", "means": "健身动作：原地跑，大腿抬至与地面平行。30 秒。" }
  ],
  "safety_note": "黄暴档 20/100(极低): 所有惩罚均为健身动作(波比跳/平板支撑/开合跳/高抬腿)，无身体接触、无羞辱性内容。每人每轮有权说「跳过」，代价是放弃本轮积分(温和替代)。未点名任何真人、无版权引用。"
}