{
  "game_title": "颗粒度大比拼",
  "subtitle": "为公司团建现制 · 5人竞猜场",
  "premise": "每人背后藏一个'办公室密码'——MBTI性格、工作作风、隐藏爱好混在一起。轮流说黑话、做任务来暗示自己是谁，其他人同时猜。猜对得分，说的人也得分。谁把自己的'颗粒度'拆得最细致，大家就猜得越准。",
  "players": ["阿凯", "琳琳", "老周", "小雨", "Tony"],
  "props_dealt": [
    {
      "prop": "密语卡",
      "to": "全体",
      "visibility": "自己看",
      "note": "每人收一张，上面写你的'办公室人设'。自己悄悄看，不要让别人看到卡面。"
    },
    {
      "prop": "匿名投票器",
      "to": "全体",
      "visibility": "自己看",
      "note": "每轮发话人说完提示后，其他4人各自在投票器上投一票'这是谁'，同时提交后一起亮票看结果。"
    },
    {
      "prop": "沙漏",
      "to": "公共区",
      "visibility": "全场公开",
      "note": "计时工具。每个发话人的说话时间不超过时间限制。"
    },
    {
      "prop": "记分板",
      "to": "公共区",
      "visibility": "全场公开",
      "note": "记录每轮的得分。"
    }
  ],
  "flow": [
    "开局：发密语卡给全体，每人看自己的'办公室人设'(30秒)。这是你这一整局的隐藏身份，不能直接说出来。",
    "第1轮~第5轮：依座位顺序，轮流一个人作'发话人'。其他4人是'猜手'。",
    "每轮流程：",
    "  ① 发话人要在30秒内说一句或多句公司常用的黑话(如'对齐''颗粒度''闭环')，来间接暗示自己的身份。或者选择做一个快速任务(15秒)来暗示。",
    "  ② 4个猜手各自在投票器上秘密投票'你猜发话人属于哪个身份'，投票不能互相看，投完一起亮票。",
    "  ③ 统计票数。猜对发话人的人各+1分；如果发话人被多数票指中，发话人也+2分。票数相同(并列)由系统随机裁决哪个是'多数'。",
    "所有5人都轮转发话1遍后，全局结束。得分最高者赢。平分由系统随机裁决赢家。"
  ],
  "rules": [
    {
      "flavor_name": "黑话密码",
      "mechanic": "同时提交",
      "plain_rule": "发话人可以选择说公司黑话，或选择做一个动作任务。说黑话就说1~3句你平时在会议里听到的词(办公室常见术语、行业缩写、工作流程用语等)。做任务就是做一个15秒的快速动作/表演/描述(如学个短视频手势、说个八卦观点、做个健身动作)来暗示你的身份。说完或做完后，其他4个猜手各自不看别人，独立在投票器上投'你猜这是谁'，然后同时亮票。",
      "visibility": "全场公开"
    },
    {
      "flavor_name": "时间压力",
      "mechanic": "限时",
      "plain_rule": "发话人说黑话不超过30秒；选择做任务必须在15秒内完成。沙漏计时，时间一到立即停止，无论说完没说完、做完没做完。",
      "visibility": "全场公开"
    },
    {
      "flavor_name": "计分细则",
      "mechanic": "加减分",
      "plain_rule": "每轮投票后亮票。投票结果中，猜对发话人的每个人+1分。如果发话人被多数票猜中(票数最多的那个身份)+2分。如果票数出现平手(两个或以上选择票数相同)，系统随机选一个当作'多数'。最终得分最高者赢；如果总分相同，系统随机选一人当赢家。",
      "visibility": "全场公开"
    },
    {
      "flavor_name": "身份摊牌",
      "mechanic": "揭示",
      "plain_rule": "5轮全部完成后，依座位顺序，每个人轮流翻开自己的密语卡，公开说出'我的身份是XX'。其他人看到真实身份后会恍然大悟。然后统计最终得分。",
      "visibility": "全场公开"
    }
  ],
  "reveal_text": "会议室的下午茶时间，每个人都藏着一个小秘密。阿凯在'对齐全组健身计划'，琳琳在模仿最新的短视频舞蹈，老周不停重复'颗粒度必须落地''这件事要闭环'，小雨眼神闪闪发光——她已经开始八卦了。Tony的健身铃铃声为整局配上了节拍。5轮后，当所有身份都摊开，大家笑着拍桌子：'哎哟，我就差一点猜对你！'",
  "reveal_signature": "融合自 阿凯 的「MBTI贴标签」× 老周 的「对齐颗粒度闭环黑话」× 琳琳 的「短视频挑战」× 小雨 的「爱吃瓜八卦」× Tony 的「健身狂魔拉人」",
  "flavor_glossary": [
    { "term": "对齐", "means": "办公室最常说的词——统一意见、保持一致。这里指通过猜测让大家对齐彼此的认知。" },
    { "term": "颗粒度", "means": "办公室术语——信息的细致程度、粒度大小。这局就是在比谁把自己的特质拆得最细，让别人猜得最准。" },
    { "term": "闭环", "means": "又一个办公室黑话——把一件事从头到尾完整处理、收尾。这局的每轮流程(说→投票→亮票→计分)就是一个完整的闭环。" },
    { "term": "MBTI", "means": "人格分类系统，用4个二元维度区分不同性格(内向/外向、感觉/直觉等)。这群人天天用这个互相贴标签。" }
  ],
  "safety_note": "黄暴档 20/100(极低): 无惩罚、无强制点名、无露骨内容。任务全是'说句话''做个动作'的低风险类型。职场语境、设计时完全避开了高羞耻感。未涉及真人、无版权歌词、无负面刻板标签。所有任务参与者可选。"
}
